tq42/__init__.py
tq42/channel.py
tq42/cli/__init__.py
tq42/cli/auth_group.py
tq42/cli/completion.py
tq42/cli/dataset_group.py
tq42/cli/entrypoint.py
tq42/cli/environment_group.py
tq42/cli/experiment_group.py
tq42/cli/experiment_run_group.py
tq42/cli/model_group.py
tq42/cli/organization_group.py
tq42/cli/project_group.py
tq42/cli/utils/__init__.py
tq42/cli/utils/cli_functions.py
tq42/cli/utils/formatter.py
tq42/cli/utils/types.py
tq42/client.py
tq42/dataset.py
tq42/exceptions/__init__.py
tq42/exceptions/authentication_error.py
tq42/exceptions/experiment_run_cancel_error.py
tq42/exceptions/invalid_argument_error.py
tq42/exceptions/no_default_error.py
tq42/exceptions/permission_denied_error.py
tq42/exceptions/retries_exceeded_error.py
tq42/exceptions/tq42_api_error.py
tq42/exceptions/unauthenticated_error.py
tq42/experiment.py
tq42/experiment_run.py
tq42/functional_tests/__init__.py
tq42/functional_tests/conftest.py
tq42/functional_tests/functional_test_config.py
tq42/functional_tests/invoke_cli/__init__.py
tq42/functional_tests/invoke_cli/test_functional_cli.py
tq42/functional_tests/invoke_cli/test_functional_experiment_group.py
tq42/functional_tests/invoke_cli/test_functional_experiment_run_group.py
tq42/functional_tests/invoke_cli/test_functional_organization_group.py
tq42/functional_tests/invoke_cli/test_functional_project_group.py
tq42/functional_tests/test_algorithms/circuit_runner/test_circuit_runner_algorithm.py
tq42/functional_tests/test_algorithms/cva_opt/test_cva_opt_algorithm.py
tq42/functional_tests/test_algorithms/optimax/test_optimax_algorithm.py
tq42/functional_tests/test_algorithms/quenc/test_quenc_algorithm.py
tq42/functional_tests/test_algorithms/routing/data.json
tq42/functional_tests/test_algorithms/routing/test_routing_algorithm.py
tq42/functional_tests/test_algorithms/tetra_opt/test_tetra_opt_algorithm.py
tq42/functional_tests/test_algorithms/toy/test_toy_algorithm.py
tq42/functional_tests/test_channels.py
tq42-0.9.15.dist-info/LICENSE
tq42-0.9.15.dist-info/METADATA
tq42-0.9.15.dist-info/WHEEL
tq42-0.9.15.dist-info/entry_points.txt
tq42-0.9.15.dist-info/RECORD
