Metadata-Version: 2.3
Name: tq42
Version: 0.9.15
Summary: tq42 sdk
Author: Terra Quantum AG
Requires-Python: >=3.8,<4.0
Classifier: Programming Language :: Python :: 3
Classifier: Programming Language :: Python :: 3.8
Classifier: Programming Language :: Python :: 3.9
Classifier: Programming Language :: Python :: 3.10
Classifier: Programming Language :: Python :: 3.11
Classifier: Programming Language :: Python :: 3.12
Classifier: Programming Language :: Python :: 3.13
Requires-Dist: PyYAML (>=6.0.1,<7.0.0)
Requires-Dist: click (>=8.1.7,<9.0.0)
Requires-Dist: grpcio (==1.64.1)
Requires-Dist: keyring (>=25.0.0,<26.0.0)
Requires-Dist: pytest (>=7.4.4,<8.0.0)
Requires-Dist: pytest-asyncio (>=0.23.7,<0.24.0)
Requires-Dist: requests (>=2.31.0,<3.0.0)
Requires-Dist: tq42_grpc_client (==1.0.269)
Requires-Dist: tqdm (>=4.66.4,<5.0.0)
Requires-Dist: validators (>=0.28.3,<0.29.0)
